filedir/__init__.py
filedir/main.py
filedir-0.0.3.dist-info/LICENSE
filedir-0.0.3.dist-info/METADATA
filedir-0.0.3.dist-info/WHEEL
filedir-0.0.3.dist-info/top_level.txt
filedir-0.0.3.dist-info/RECORD
