Metadata-Version: 2.1
Name: filedir
Version: 0.0.3
Summary: Filedir is a python module to work with files and directories.
Home-page: UNKNOWN
Author: Dlurak
License: UNKNOWN
Keywords: python,files,directorys,folders,sorting
Platform: UNKNOWN
Classifier: Development Status :: 3 - Alpha
Classifier: Intended Audience :: Developers
Classifier: Programming Language :: Python :: 3
Classifier: Operating System :: Unix
Classifier: Operating System :: MacOS :: MacOS X
Classifier: Operating System :: Microsoft :: Windows
Classifier: License :: OSI Approved :: Mozilla Public License 2.0 (MPL 2.0)
Classifier: Natural Language :: English
